odoo/addons/l10n_fr_account_vat_return_teledec/README.rst
odoo/addons/l10n_fr_account_vat_return_teledec/__init__.py
odoo/addons/l10n_fr_account_vat_return_teledec/__manifest__.py
odoo/addons/l10n_fr_account_vat_return_teledec/i18n/fr.po
odoo/addons/l10n_fr_account_vat_return_teledec/i18n/l10n_fr_account_vat_return_teledec.pot
odoo/addons/l10n_fr_account_vat_return_teledec/models/__init__.py
odoo/addons/l10n_fr_account_vat_return_teledec/models/l10n_fr_account_vat_return.py
odoo/addons/l10n_fr_account_vat_return_teledec/models/res_company.py
odoo/addons/l10n_fr_account_vat_return_teledec/readme/CONFIGURE.rst
odoo/addons/l10n_fr_account_vat_return_teledec/readme/CONTRIBUTORS.rst
odoo/addons/l10n_fr_account_vat_return_teledec/readme/DESCRIPTION.rst
odoo/addons/l10n_fr_account_vat_return_teledec/readme/USAGE.rst
odoo/addons/l10n_fr_account_vat_return_teledec/static/description/icon.png
odoo/addons/l10n_fr_account_vat_return_teledec/static/description/index.html
odoo/addons/l10n_fr_account_vat_return_teledec/static/description/transmit_teledec_button.png
odoo/addons/l10n_fr_account_vat_return_teledec/views/l10n_fr_account_vat_return.xml
odoo/addons/l10n_fr_account_vat_return_teledec/wizards/__init__.py
odoo/addons/l10n_fr_account_vat_return_teledec/wizards/res_config_settings.py
odoo/addons/l10n_fr_account_vat_return_teledec/wizards/res_config_settings.xml
odoo14_addon_l10n_fr_account_vat_return_teledec-14.0.1.1.0.dist-info/METADATA
odoo14_addon_l10n_fr_account_vat_return_teledec-14.0.1.1.0.dist-info/WHEEL
odoo14_addon_l10n_fr_account_vat_return_teledec-14.0.1.1.0.dist-info/top_level.txt
odoo14_addon_l10n_fr_account_vat_return_teledec-14.0.1.1.0.dist-info/RECORD
